netlasso/__init__.py
netlasso/api.py
netlasso/coreutils.py
netlasso/netlasso.py
netlasso-1.4.0.dist-info/LICENSE
netlasso-1.4.0.dist-info/METADATA
netlasso-1.4.0.dist-info/WHEEL
netlasso-1.4.0.dist-info/entry_points.txt
netlasso-1.4.0.dist-info/RECORD
