Metadata-Version: 2.1
Name: netlasso
Version: 1.4.0
Summary: Perform advanced searches for internet-connected (IoT) devices based on user-provided search queries.
Home-page: https://pypi.org/project/netlasso
License: MIT
Keywords: iot,internet-of-things,netlas-io-api,netlas-io,netlas
Author: Richard Mwewa
Author-email: rly0nheart@duck.com
Requires-Python: >=3.10,<4.0
Classifier: Development Status :: 5 - Production/Stable
Classifier: Intended Audience :: Information Technology
Classifier: License :: OSI Approved :: MIT License
Classifier: Natural Language :: English
Classifier: Operating System :: OS Independent
Classifier: Programming Language :: Python :: 3
Classifier: Programming Language :: Python :: 3.10
Classifier: Programming Language :: Python :: 3.11
Classifier: Programming Language :: Python :: 3.12
Requires-Dist: aiohttp
Requires-Dist: rich
Requires-Dist: rich-argparse
Project-URL: Documentation, https://github.com/rly0nheart/netlasso/blob/master/README.md
Project-URL: Repository, https://github.com/rly0nheart/netlasso
